wpilog/__init__.py
wpilog/version.py
wpilog/_init__wpilog.py
wpilog/_wpilog.cpython-312-darwin.so
wpilog/_wpilog.pyi
wpilog/wpilog.pc
wpilog/trampolines/wpi__log__BooleanArrayLogEntry.hpp
wpilog/trampolines/wpi__log__BooleanLogEntry.hpp
wpilog/trampolines/wpi__log__DataLog.hpp
wpilog/trampolines/wpi__log__DataLogBackgroundWriter.hpp
wpilog/trampolines/wpi__log__DataLogEntry.hpp
wpilog/trampolines/wpi__log__DataLogReader.hpp
wpilog/trampolines/wpi__log__DataLogRecord.hpp
wpilog/trampolines/wpi__log__DataLogValueEntryImpl.hpp
wpilog/trampolines/wpi__log__DataLogWriter.hpp
wpilog/trampolines/wpi__log__DoubleArrayLogEntry.hpp
wpilog/trampolines/wpi__log__DoubleLogEntry.hpp
wpilog/trampolines/wpi__log__FloatArrayLogEntry.hpp
wpilog/trampolines/wpi__log__FloatLogEntry.hpp
wpilog/trampolines/wpi__log__IntegerArrayLogEntry.hpp
wpilog/trampolines/wpi__log__IntegerLogEntry.hpp
wpilog/trampolines/wpi__log__MetadataRecordData.hpp
wpilog/trampolines/wpi__log__RawLogEntry.hpp
wpilog/trampolines/wpi__log__StartRecordData.hpp
wpilog/trampolines/wpi__log__StringArrayLogEntry.hpp
wpilog/trampolines/wpi__log__StringLogEntry.hpp
wpilog/trampolines/wpi__log__StructArrayLogEntry.hpp
wpilog/trampolines/wpi__log__StructLogEntry.hpp
robotpy_wpilog-2027.0.0a2.dist-info/METADATA
robotpy_wpilog-2027.0.0a2.dist-info/WHEEL
robotpy_wpilog-2027.0.0a2.dist-info/entry_points.txt
robotpy_wpilog-2027.0.0a2.dist-info/RECORD
