Metadata-Version: 2.4
Name: robotpy-wpilog
Version: 2027.0.0a2
Summary: Binary wrapper for FRC wpilog library
Project-URL: Source code, https://github.com/robotpy/mostrobotpy
Author-email: RobotPy Development Team <robotpy@googlegroups.com>
License-Expression: BSD-3-Clause
Requires-Dist: robotpy-native-datalog==2027.0.0a2
Requires-Dist: robotpy-wpiutil==2027.0.0a2
